Workbook

Sheet Read me
A1: Phase 2 gate: moving-average crossover, checked by hand
A3: The 'Calc' sheet replays the strategy one candle per row using only the prices and the settings.
A4: Each candle: (1) at the open, carry out orders decided at the previous close: exits first, then entries;
A5: (2) during the candle, close the trade if the low reaches the stop-loss (at the open if it gapped below);
A6: (3) at the close, decide what to do at the next open.
A7: Buy price = open × (1 + spread/2 + slippage). Sell price = price × (1 − spread/2 − slippage).
A8: Size = cash × risk ÷ (buy price − stop), capped so the position is at most 30× cash.
A9: Financing = units × open price at entry × rate ÷ 365 × nights held. Commission on every order.
A10: The 'Trades' sheet puts the app's results beside the spreadsheet's. The 'Summary' sheet (last tab) shows whether they all match.
A11: Prices: made-up sample data for EUR/GBP (priced in pounds). The arithmetic is what's being checked.
A12: Yellow cells on 'Inputs' are the settings; change one and both columns would need re-running the app to compare.

Sheet Inputs
A1: Setting | B1: Value
A2: Start balance (£) | B2: 1000
A3: Risk per trade | B3: 0.01
A4: Fast average (candles) | B4: 20
A5: Slow average (candles) | B5: 50
A6: Stop distance (× ATR 14) | B6: 2
A7: Spread (%) | B7: 0.02
A8: Slippage (%) | B8: 0.01
A9: Commission (£ per order) | B9: 1
A10: Overnight financing (% a year) | B10: 6.5
A11: Leverage cap (× balance) | B11: 30
A12: Price adjustment per order (spread/2 + slippage) | B12: =Inputs!$B$7/200+Inputs!$B$8/100 -> 0.0002
A13: Financing per £ per night | B13: =Inputs!$B$10/100/365 -> 0.00017808219

Sheet Calc
A1: Date | B1: Open | C1: High | D1: Low | E1: Close | F1: Fast avg | G1: Slow avg | H1: True range | I1: ATR 14 | J1: Crossed up | K1: Crossed down | L1: Stop if bought | M1: Exit at open? | N1: Sell fill at open | O1: Cash change: exit at open | P1: Cash after open exit | Q1: Buy at open? | R1: Buy fill | S1: Units bought | T1: Units held | U1: Stop-loss | V1: Stop hit? | W1: Cash change: stop-loss | X1: Cash at close | Y1: Units at close | Z1: Sell at next open? | AA1: Buy at next open? | AB1: Entry fill | AC1: Entry date | AD1: Entry open | AE1: Stop for next buy | AF1: Stop carried | AG1: Trade no. | AH1: Trade no. before open | AI1: Equity | AJ1: Cash change: end of test | AK1: Sell fill if stopped
A2: Start | X2: =Inputs!$B$2 -> 1000 | Y2: 0 | Z2: =FALSE() -> FALSE | AA2: =FALSE() -> FALSE | AB2: 0 | AC2: 0 | AD2: 0 | AG2: 0
A3: 44787 | B3: 0.82773768 | C3: 0.83173112 | D3: 0.82205554 | E3: 0.83085197 | F3: =IF(ROW()-2>=Inputs!$B$4,AVERAGE(OFFSET(E3,1-Inputs!$B$4,0,Inputs!$B$4,1)),"") | G3: =IF(ROW()-2>=Inputs!$B$5,AVERAGE(OFFSET(E3,1-Inputs!$B$5,0,Inputs!$B$5,1)),"") | H3: =C3-D3 -> 0.0096755803 | I3: =IF(ROW()-2<14,"",IF(ROW()-2=14,AVERAGE(OFFSET(H3,-13,0,14,1)),(I2*13+H3)/14)) | J3: =IF(AND(ISNUMBER(F3),ISNUMBER(G3),ISNUMBER(F2),ISNUMBER(G2)),AND(F3>G3,F2<=G2),FALSE()) -> FALSE | K3: =IF(AND(ISNUMBER(F3),ISNUMBER(G3),ISNUMBER(F2),ISNUMBER(G2)),AND(F3<G3,F2>=G2),FALSE()) -> FALSE | L3: =IF(ISNUMBER(I3),E3-Inputs!$B$6*I3,"") | M3: =AND(Y2>0,Z2) -> FALSE | N3: =B3*(1-Inputs!$B$12) -> 0.82757213 | O3: =IF(M3,Y2*(N3-AB2)-Inputs!$B$9-Y2*AD2*Inputs!$B$13*(A3-AC2),0) -> 0 | P3: =X2+O3 -> 1000 | Q3: =AND(IF(M3,0,Y2)=0,AA2,IF(ISNUMBER(AE2),B3>AE2,FALSE())) -> FALSE | R3: =B3*(1+Inputs!$B$12) -> 0.82790323 | S3: =IF(Q3,MIN(P3*Inputs!$B$3/(R3-AE2),P3*Inputs!$B$11/R3),0) -> 0 | T3: =IF(Q3,S3,IF(M3,0,Y2)) -> 0 | U3: =IF(Q3,AE2,AF2) -> 0 | V3: =AND(T3>0,D3<=U3) -> FALSE | W3: =IF(V3,T3*(AK3-AB3)-Inputs!$B$9-T3*AD3*Inputs!$B$13*(A3-AC3),0) -> 0 | X3: =P3-IF(Q3,Inputs!$B$9,0)+W3 -> 1000 | Y3: =IF(V3,0,T3) -> 0 | Z3: =AND(Y3>0,K3) -> FALSE | AA3: =AND(Y3=0,J3,ISNUMBER(L3)) -> FALSE | AB3: =IF(Q3,R3,AB2) -> 0 | AC3: =IF(Q3,A3,AC2) -> 0 | AD3: =IF(Q3,B3,AD2) -> 0 | AE3: =IF(AA3,L3,"") | AF3: =U3 -> 0 | AG3: =AG2+IF(Q3,1,0) -> 0 | AH3: =AG2 -> 0 | AI3: =X3+Y3*(E3-AB3)-Y3*AD3*Inputs!$B$13*(A3-AC3) -> 1000 | AJ3: 0 | AK3: =IF(AND(B3<=U3,NOT(Q3)),B3,U3)*(1-Inputs!$B$12) -> 0
A4: 44788 | B4: 0.83085197 | C4: 0.83543103 | D4: 0.82857927 | E4: 0.83445608 | F4: =IF(ROW()-2>=Inputs!$B$4,AVERAGE(OFFSET(E4,1-Inputs!$B$4,0,Inputs!$B$4,1)),"") | G4: =IF(ROW()-2>=Inputs!$B$5,AVERAGE(OFFSET(E4,1-Inputs!$B$5,0,Inputs!$B$5,1)),"") | H4: =MAX(C4-D4,ABS(C4-E3),ABS(D4-E3)) -> 0.0068517664 | I4: =IF(ROW()-2<14,"",IF(ROW()-2=14,AVERAGE(OFFSET(H4,-13,0,14,1)),(I3*13+H4)/14)) | J4: =IF(AND(ISNUMBER(F4),ISNUMBER(G4),ISNUMBER(F3),ISNUMBER(G3)),AND(F4>G4,F3<=G3),FALSE()) -> FALSE | K4: =IF(AND(ISNUMBER(F4),ISNUMBER(G4),ISNUMBER(F3),ISNUMBER(G3)),AND(F4<G4,F3>=G3),FALSE()) -> FALSE | L4: =IF(ISNUMBER(I4),E4-Inputs!$B$6*I4,"") | M4: =AND(Y3>0,Z3) -> FALSE | N4: =B4*(1-Inputs!$B$12) -> 0.8306858 | O4: =IF(M4,Y3*(N4-AB3)-Inputs!$B$9-Y3*AD3*Inputs!$B$13*(A4-AC3),0) -> 0 | P4: =X3+O4 -> 1000 | Q4: =AND(IF(M4,0,Y3)=0,AA3,IF(ISNUMBER(AE3),B4>AE3,FALSE())) -> FALSE | R4: =B4*(1+Inputs!$B$12) -> 0.83101814 | S4: =IF(Q4,MIN(P4*Inputs!$B$3/(R4-AE3),P4*Inputs!$B$11/R4),0) -> 0 | T4: =IF(Q4,S4,IF(M4,0,Y3)) -> 0 | U4: =IF(Q4,AE3,AF3) -> 0 | V4: =AND(T4>0,D4<=U4) -> FALSE | W4: =IF(V4,T4*(AK4-AB4)-Inputs!$B$9-T4*AD4*Inputs!$B$13*(A4-AC4),0) -> 0 | X4: =P4-IF(Q4,Inputs!$B$9,0)+W4 -> 1000 | Y4: =IF(V4,0,T4) -> 0 | Z4: =AND(Y4>0,K4) -> FALSE | AA4: =AND(Y4=0,J4,ISNUMBER(L4)) -> FALSE | AB4: =IF(Q4,R4,AB3) -> 0 | AC4: =IF(Q4,A4,AC3) -> 0 | AD4: =IF(Q4,B4,AD3) -> 0 | AE4: =IF(AA4,L4,"") | AF4: =U4 -> 0 | AG4: =AG3+IF(Q4,1,0) -> 0 | AH4: =AG3 -> 0 | AI4: =X4+Y4*(E4-AB4)-Y4*AD4*Inputs!$B$13*(A4-AC4) -> 1000 | AJ4: 0 | AK4: =IF(AND(B4<=U4,NOT(Q4)),B4,U4)*(1-Inputs!$B$12) -> 0
A5: 44789 | B5: 0.83445608 | C5: 0.84471166 | D5: 0.83006435 | E5: 0.8437461 | F5: =IF(ROW()-2>=Inputs!$B$4,AVERAGE(OFFSET(E5,1-Inputs!$B$4,0,Inputs!$B$4,1)),"") | G5: =IF(ROW()-2>=Inputs!$B$5,AVERAGE(OFFSET(E5,1-Inputs!$B$5,0,Inputs!$B$5,1)),"") | H5: =MAX(C5-D5,ABS(C5-E4),ABS(D5-E4)) -> 0.01464731 | I5: =IF(ROW()-2<14,"",IF(ROW()-2=14,AVERAGE(OFFSET(H5,-13,0,14,1)),(I4*13+H5)/14)) | J5: =IF(AND(ISNUMBER(F5),ISNUMBER(G5),ISNUMBER(F4),ISNUMBER(G4)),AND(F5>G5,F4<=G4),FALSE()) -> FALSE | K5: =IF(AND(ISNUMBER(F5),ISNUMBER(G5),ISNUMBER(F4),ISNUMBER(G4)),AND(F5<G5,F4>=G4),FALSE()) -> FALSE | L5: =IF(ISNUMBER(I5),E5-Inputs!$B$6*I5,"") | M5: =AND(Y4>0,Z4) -> FALSE | N5: =B5*(1-Inputs!$B$12) -> 0.83428919 | O5: =IF(M5,Y4*(N5-AB4)-Inputs!$B$9-Y4*AD4*Inputs!$B$13*(A5-AC4),0) -> 0 | P5: =X4+O5 -> 1000 | Q5: =AND(IF(M5,0,Y4)=0,AA4,IF(ISNUMBER(AE4),B5>AE4,FALSE())) -> FALSE | R5: =B5*(1+Inputs!$B$12) -> 0.83462298 | S5: =IF(Q5,MIN(P5*Inputs!$B$3/(R5-AE4),P5*Inputs!$B$11/R5),0) -> 0 | T5: =IF(Q5,S5,IF(M5,0,Y4)) -> 0 | U5: =IF(Q5,AE4,AF4) -> 0 | V5: =AND(T5>0,D5<=U5) -> FALSE | W5: =IF(V5,T5*(AK5-AB5)-Inputs!$B$9-T5*AD5*Inputs!$B$13*(A5-AC5),0) -> 0 | X5: =P5-IF(Q5,Inputs!$B$9,0)+W5 -> 1000 | Y5: =IF(V5,0,T5) -> 0 | Z5: =AND(Y5>0,K5) -> FALSE | AA5: =AND(Y5=0,J5,ISNUMBER(L5)) -> FALSE | AB5: =IF(Q5,R5,AB4) -> 0 | AC5: =IF(Q5,A5,AC4) -> 0 | AD5: =IF(Q5,B5,AD4) -> 0 | AE5: =IF(AA5,L5,"") | AF5: =U5 -> 0 | AG5: =AG4+IF(Q5,1,0) -> 0 | AH5: =AG4 -> 0 | AI5: =X5+Y5*(E5-AB5)-Y5*AD5*Inputs!$B$13*(A5-AC5) -> 1000 | AJ5: 0 | AK5: =IF(AND(B5<=U5,NOT(Q5)),B5,U5)*(1-Inputs!$B$12) -> 0
A6: 44790 | B6: 0.8437461 | C6: 0.8471835 | D6: 0.83259534 | E6: 0.83520156 | F6: =IF(ROW()-2>=Inputs!$B$4,AVERAGE(OFFSET(E6,1-Inputs!$B$4,0,Inputs!$B$4,1)),"") | G6: =IF(ROW()-2>=Inputs!$B$5,AVERAGE(OFFSET(E6,1-Inputs!$B$5,0,Inputs!$B$5,1)),"") | H6: =MAX(C6-D6,ABS(C6-E5),ABS(D6-E5)) -> 0.014588152 | I6: =IF(ROW()-2<14,"",IF(ROW()-2=14,AVERAGE(OFFSET(H6,-13,0,14,1)),(I5*13+H6)/14)) | J6: =IF(AND(ISNUMBER(F6),ISNUMBER(G6),ISNUMBER(F5),ISNUMBER(G5)),AND(F6>G6,F5<=G5),FALSE()) -> FALSE | K6: =IF(AND(ISNUMBER(F6),ISNUMBER(G6),ISNUMBER(F5),ISNUMBER(G5)),AND(F6<G6,F5>=G5),FALSE()) -> FALSE | L6: =IF(ISNUMBER(I6),E6-Inputs!$B$6*I6,"") | M6: =AND(Y5>0,Z5) -> FALSE | N6: =B6*(1-Inputs!$B$12) -> 0.84357735 | O6: =IF(M6,Y5*(N6-AB5)-Inputs!$B$9-Y5*AD5*Inputs!$B$13*(A6-AC5),0) -> 0 | P6: =X5+O6 -> 1000 | Q6: =AND(IF(M6,0,Y5)=0,AA5,IF(ISNUMBER(AE5),B6>AE5,FALSE())) -> FALSE | R6: =B6*(1+Inputs!$B$12) -> 0.84391485 | S6: =IF(Q6,MIN(P6*Inputs!$B$3/(R6-AE5),P6*Inputs!$B$11/R6),0) -> 0 | T6: =IF(Q6,S6,IF(M6,0,Y5)) -> 0 | U6: =IF(Q6,AE5,AF5) -> 0 | V6: =AND(T6>0,D6<=U6) -> FALSE | W6: =IF(V6,T6*(AK6-AB6)-Inputs!$B$9-T6*AD6*Inputs!$B$13*(A6-AC6),0) -> 0 | X6: =P6-IF(Q6,Inputs!$B$9,0)+W6 -> 1000 | Y6: =IF(V6,0,T6) -> 0 | Z6: =AND(Y6>0,K6) -> FALSE | AA6: =AND(Y6=0,J6,ISNUMBER(L6)) -> FALSE | AB6: =IF(Q6,R6,AB5) -> 0 | AC6: =IF(Q6,A6,AC5) -> 0 | AD6: =IF(Q6,B6,AD5) -> 0 | AE6: =IF(AA6,L6,"") | AF6: =U6 -> 0 | AG6: =AG5+IF(Q6,1,0) -> 0 | AH6: =AG5 -> 0 | AI6: =X6+Y6*(E6-AB6)-Y6*AD6*Inputs!$B$13*(A6-AC6) -> 1000 | AJ6: 0 | AK6: =IF(AND(B6<=U6,NOT(Q6)),B6,U6)*(1-Inputs!$B$12) -> 0
A7: 44791 | B7: 0.83520156 | C7: 0.84206671 | D7: 0.8281703 | E7: 0.8305867 | F7: =IF(ROW()-2>=Inputs!$B$4,AVERAGE(OFFSET(E7,1-Inputs!$B$4,0,Inputs!$B$4,1)),"") | G7: =IF(ROW()-2>=Inputs!$B$5,AVERAGE(OFFSET(E7,1-Inputs!$B$5,0,Inputs!$B$5,1)),"") | H7: =MAX(C7-D7,ABS(C7-E6),ABS(D7-E6)) -> 0.013896406 | I7: =IF(ROW()-2<14,"",IF(ROW()-2=14,AVERAGE(OFFSET(H7,-13,0,14,1)),(I6*13+H7)/14)) | J7: =IF(AND(ISNUMBER(F7),ISNUMBER(G7),ISNUMBER(F6),ISNUMBER(G6)),AND(F7>G7,F6<=G6),FALSE()) -> FALSE | K7: =IF(AND(ISNUMBER(F7),ISNUMBER(G7),ISNUMBER(F6),ISNUMBER(G6)),AND(F7<G7,F6>=G6),FALSE()) -> FALSE | L7: =IF(ISNUMBER(I7),E7-Inputs!$B$6*I7,"") | M7: =AND(Y6>0,Z6) -> FALSE | N7: =B7*(1-Inputs!$B$12) -> 0.83503452 | O7: =IF(M7,Y6*(N7-AB6)-Inputs!$B$9-Y6*AD6*Inputs!$B$13*(A7-AC6),0) -> 0 | P7: =X6+O7 -> 1000 | Q7: =AND(IF(M7,0,Y6)=0,AA6,IF(ISNUMBER(AE6),B7>AE6,FALSE())) -> FALSE | R7: =B7*(1+Inputs!$B$12) -> 0.8353686 | S7: =IF(Q7,MIN(P7*Inputs!$B$3/(R7-AE6),P7*Inputs!$B$11/R7),0) -> 0 | T7: =IF(Q7,S7,IF(M7,0,Y6)) -> 0 | U7: =IF(Q7,AE6,AF6) -> 0 | V7: =AND(T7>0,D7<=U7) -> FALSE | W7: =IF(V7,T7*(AK7-AB7)-Inputs!$B$9-T7*AD7*Inputs!$B$13*(A7-AC7),0) -> 0 | X7: =P7-IF(Q7,Inputs!$B$9,0)+W7 -> 1000 | Y7: =IF(V7,0,T7) -> 0 | Z7: =AND(Y7>0,K7) -> FALSE | AA7: =AND(Y7=0,J7,ISNUMBER(L7)) -> FALSE | AB7: =IF(Q7,R7,AB6) -> 0 | AC7: =IF(Q7,A7,AC6) -> 0 | AD7: =IF(Q7,B7,AD6) -> 0 | AE7: =IF(AA7,L7,"") | AF7: =U7 -> 0 | AG7: =AG6+IF(Q7,1,0) -> 0 | AH7: =AG6 -> 0 | AI7: =X7+Y7*(E7-AB7)-Y7*AD7*Inputs!$B$13*(A7-AC7) -> 1000 | AJ7: 0 | AK7: =IF(AND(B7<=U7,NOT(Q7)),B7,U7)*(1-Inputs!$B$12) -> 0
A8: 44792 | B8: 0.8305867 | C8: 0.83538128 | D8: 0.8277812 | E8: 0.83193778 | F8: =IF(ROW()-2>=Inputs!$B$4,AVERAGE(OFFSET(E8,1-Inputs!$B$4,0,Inputs!$B$4,1)),"") | G8: =IF(ROW()-2>=Inputs!$B$5,AVERAGE(OFFSET(E8,1-Inputs!$B$5,0,Inputs!$B$5,1)),"") | H8: =MAX(C8-D8,ABS(C8-E7),ABS(D8-E7)) -> 0.0076000789 | I8: =IF(ROW()-2<14,"",IF(ROW()-2=14,AVERAGE(OFFSET(H8,-13,0,14,1)),(I7*13+H8)/14)) | J8: =IF(AND(ISNUMBER(F8),ISNUMBER(G8),ISNUMBER(F7),ISNUMBER(G7)),AND(F8>G8,F7<=G7),FALSE()) -> FALSE | K8: =IF(AND(ISNUMBER(F8),ISNUMBER(G8),ISNUMBER(F7),ISNUMBER(G7)),AND(F8<G8,F7>=G7),FALSE()) -> FALSE | L8: =IF(ISNUMBER(I8),E8-Inputs!$B$6*I8,"") | M8: =AND(Y7>0,Z7) -> FALSE | N8: =B8*(1-Inputs!$B$12) -> 0.83042059 | O8: =IF(M8,Y7*(N8-AB7)-Inputs!$B$9-Y7*AD7*Inputs!$B$13*(A8-AC7),0) -> 0 | P8: =X7+O8 -> 1000 | Q8: =AND(IF(M8,0,Y7)=0,AA7,IF(ISNUMBER(AE7),B8>AE7,FALSE())) -> FALSE | R8: =B8*(1+Inputs!$B$12) -> 0.83075282 | S8: =IF(Q8,MIN(P8*Inputs!$B$3/(R8-AE7),P8*Inputs!$B$11/R8),0) -> 0 | T8: =IF(Q8,S8,IF(M8,0,Y7)) -> 0 | U8: =IF(Q8,AE7,AF7) -> 0 | V8: =AND(T8>0,D8<=U8) -> FALSE | W8: =IF(V8,T8*(AK8-AB8)-Inputs!$B$9-T8*AD8*Inputs!$B$13*(A8-AC8),0) -> 0 | X8: =P8-IF(Q8,Inputs!$B$9,0)+W8 -> 1000 | Y8: =IF(V8,0,T8) -> 0 | Z8: =AND(Y8>0,K8) -> FALSE | AA8: =AND(Y8=0,J8,ISNUMBER(L8)) -> FALSE | AB8: =IF(Q8,R8,AB7) -> 0 | AC8: =IF(Q8,A8,AC7) -> 0 | AD8: =IF(Q8,B8,AD7) -> 0 | AE8: =IF(AA8,L8,"") | AF8: =U8 -> 0 | AG8: =AG7+IF(Q8,1,0) -> 0 | AH8: =AG7 -> 0 | AI8: =X8+Y8*(E8-AB8)-Y8*AD8*Inputs!$B$13*(A8-AC8) -> 1000 | AJ8: 0 | AK8: =IF(AND(B8<=U8,NOT(Q8)),B8,U8)*(1-Inputs!$B$12) -> 0
A9: 44793 | B9: 0.83193778 | C9: 0.84048218 | D9: 0.83180434 | E9: 0.83649161 | F9: =IF(ROW()-2>=Inputs!$B$4,AVERAGE(OFFSET(E9,1-Inputs!$B$4,0,Inputs!$B$4,1)),"") | G9: =IF(ROW()-2>=Inputs!$B$5,AVERAGE(OFFSET(E9,1-Inputs!$B$5,0,Inputs!$B$5,1)),"") | H9: =MAX(C9-D9,ABS(C9-E8),ABS(D9-E8)) -> 0.0086778436 | I9: =IF(ROW()-2<14,"",IF(ROW()-2=14,AVERAGE(OFFSET(H9,-13,0,14,1)),(I8*13+H9)/14)) | J9: =IF(AND(ISNUMBER(F9),ISNUMBER(G9),ISNUMBER(F8),ISNUMBER(G8)),AND(F9>G9,F8<=G8),FALSE()) -> FALSE | K9: =IF(AND(ISNUMBER(F9),ISNUMBER(G9),ISNUMBER(F8),ISNUMBER(G8)),AND(F9<G9,F8>=G8),FALSE()) -> FALSE | L9: =IF(ISNUMBER(I9),E9-Inputs!$B$6*I9,"") | M9: =AND(Y8>0,Z8) -> FALSE | N9: =B9*(1-Inputs!$B$12) -> 0.8317714 | O9: =IF(M9,Y8*(N9-AB8)-Inputs!$B$9-Y8*AD8*Inputs!$B$13*(A9-AC8),0) -> 0 | P9: =X8+O9 -> 1000 | Q9: =AND(IF(M9,0,Y8)=0,AA8,IF(ISNUMBER(AE8),B9>AE8,FALSE())) -> FALSE | R9: =B9*(1+Inputs!$B$12) -> 0.83210417 | S9: =IF(Q9,MIN(P9*Inputs!$B$3/(R9-AE8),P9*Inputs!$B$11/R9),0) -> 0 | T9: =IF(Q9,S9,IF(M9,0,Y8)) -> 0 | U9: =IF(Q9,AE8,AF8) -> 0 | V9: =AND(T9>0,D9<=U9) -> FALSE | W9: =IF(V9,T9*(AK9-AB9)-Inputs!$B$9-T9*AD9*Inputs!$B$13*(A9-AC9),0) -> 0 | X9: =P9-IF(Q9,Inputs!$B$9,0)+W9 -> 1000 | Y9: =IF(V9,0,T9) -> 0 | Z9: =AND(Y9>0,K9) -> FALSE | AA9: =AND(Y9=0,J9,ISNUMBER(L9)) -> FALSE | AB9: =IF(Q9,R9,AB8) -> 0 | AC9: =IF(Q9,A9,AC8) -> 0 | AD9: =IF(Q9,B9,AD8) -> 0 | AE9: =IF(AA9,L9,"") | AF9: =U9 -> 0 | AG9: =AG8+IF(Q9,1,0) -> 0 | AH9: =AG8 -> 0 | AI9: =X9+Y9*(E9-AB9)-Y9*AD9*Inputs!$B$13*(A9-AC9) -> 1000 | AJ9: 0 | AK9: =IF(AND(B9<=U9,NOT(Q9)),B9,U9)*(1-Inputs!$B$12) -> 0
A10: 44794 | B10: 0.83649161 | C10: 0.83919543 | D10: 0.82455048 | E10: 0.83215379 | F10: =IF(ROW()-2>=Inputs!$B$4,AVERAGE(OFFSET(E10,1-Inputs!$B$4,0,Inputs!$B$4,1)),"") | G10: =IF(ROW()-2>=Inputs!$B$5,AVERAGE(OFFSET(E10,1-Inputs!$B$5,0,Inputs!$B$5,1)),"") | H10: =MAX(C10-D10,ABS(C10-E9),ABS(D10-E9)) -> 0.014644943 | I10: =IF(ROW()-2<14,"",IF(ROW()-2=14,AVERAGE(OFFSET(H10,-13,0,14,1)),(I9*13+H10)/14)) | J10: =IF(AND(ISNUMBER(F10),ISNUMBER(G10),ISNUMBER(F9),ISNUMBER(G9)),AND(F10>G10,F9<=G9),FALSE()) -> FALSE | K10: =IF(AND(ISNUMBER(F10),ISNUMBER(G10),ISNUMBER(F9),ISNUMBER(G9)),AND(F10<G10,F9>=G9),FALSE()) -> FALSE | L10: =IF(ISNUMBER(I10),E10-Inputs!$B$6*I10,"") | M10: =AND(Y9>0,Z9) -> FALSE | N10: =B10*(1-Inputs!$B$12) -> 0.83632431 | O10: =IF(M10,Y9*(N10-AB9)-Inputs!$B$9-Y9*AD9*Inputs!$B$13*(A10-AC9),0) -> 0 | P10: =X9+O10 -> 1000 | Q10: =AND(IF(M10,0,Y9)=0,AA9,IF(ISNUMBER(AE9),B10>AE9,FALSE())) -> FALSE | R10: =B10*(1+Inputs!$B$12) -> 0.83665891 | S10: =IF(Q10,MIN(P10*Inputs!$B$3/(R10-AE9),P10*Inputs!$B$11/R10),0) -> 0 | T10: =IF(Q10,S10,IF(M10,0,Y9)) -> 0 | U10: =IF(Q10,AE9,AF9) -> 0 | V10: =AND(T10>0,D10<=U10) -> FALSE | W10: =IF(V10,T10*(AK10-AB10)-Inputs!$B$9-T10*AD10*Inputs!$B$13*(A10-AC10),0) -> 0 | X10: =P10-IF(Q10,Inputs!$B$9,0)+W10 -> 1000 | Y10: =IF(V10,0,T10) -> 0 | Z10: =AND(Y10>0,K10) -> FALSE | AA10: =AND(Y10=0,J10,ISNUMBER(L10)) -> FALSE | AB10: =IF(Q10,R10,AB9) -> 0 | AC10: =IF(Q10,A10,AC9) -> 0 | AD10: =IF(Q10,B10,AD9) -> 0 | AE10: =IF(AA10,L10,"") | AF10: =U10 -> 0 | AG10: =AG9+IF(Q10,1,0) -> 0 | AH10: =AG9 -> 0 | AI10: =X10+Y10*(E10-AB10)-Y10*AD10*Inputs!$B$13*(A10-AC10) -> 1000 | AJ10: 0 | AK10: =IF(AND(B10<=U10,NOT(Q10)),B10,U10)*(1-Inputs!$B$12) -> 0
A11: 44795 | B11: 0.83215379 | C11: 0.83959657 | D11: 0.83036407 | E11: 0.83930269 | F11: =IF(ROW()-2>=Inputs!$B$4,AVERAGE(OFFSET(E11,1-Inputs!$B$4,0,Inputs!$B$4,1)),"") | G11: =IF(ROW()-2>=Inputs!$B$5,AVERAGE(OFFSET(E11,1-Inputs!$B$5,0,Inputs!$B$5,1)),"") | H11: =MAX(C11-D11,ABS(C11-E10),ABS(D11-E10)) -> 0.0092324963 | I11: =IF(ROW()-2<14,"",IF(ROW()-2=14,AVERAGE(OFFSET(H11,-13,0,14,1)),(I10*13+H11)/14)) | J11: =IF(AND(ISNUMBER(F11),ISNUMBER(G11),ISNUMBER(F10),ISNUMBER(G10)),AND(F11>G11,F10<=G10),FALSE()) -> FALSE | K11: =IF(AND(ISNUMBER(F11),ISNUMBER(G11),ISNUMBER(F10),ISNUMBER(G10)),AND(F11<G11,F10>=G10),FALSE()) -> FALSE | L11: =IF(ISNUMBER(I11),E11-Inputs!$B$6*I11,"") | M11: =AND(Y10>0,Z10) -> FALSE | N11: =B11*(1-Inputs!$B$12) -> 0.83198736 | O11: =IF(M11,Y10*(N11-AB10)-Inputs!$B$9-Y10*AD10*Inputs!$B$13*(A11-AC10),0) -> 0 | P11: =X10+O11 -> 1000 | Q11: =AND(IF(M11,0,Y10)=0,AA10,IF(ISNUMBER(AE10),B11>AE10,FALSE())) -> FALSE | R11: =B11*(1+Inputs!$B$12) -> 0.83232022 | S11: =IF(Q11,MIN(P11*Inputs!$B$3/(R11-AE10),P11*Inputs!$B$11/R11),0) -> 0 | T11: =IF(Q11,S11,IF(M11,0,Y10)) -> 0 | U11: =IF(Q11,AE10,AF10) -> 0 | V11: =AND(T11>0,D11<=U11) -> FALSE | W11: =IF(V11,T11*(AK11-AB11)-Inputs!$B$9-T11*AD11*Inputs!$B$13*(A11-AC11),0) -> 0 | X11: =P11-IF(Q11,Inputs!$B$9,0)+W11 -> 1000 | Y11: =IF(V11,0,T11) -> 0 | Z11: =AND(Y11>0,K11) -> FALSE | AA11: =AND(Y11=0,J11,ISNUMBER(L11)) -> FALSE | AB11: =IF(Q11,R11,AB10) -> 0 | AC11: =IF(Q11,A11,AC10) -> 0 | AD11: =IF(Q11,B11,AD10) -> 0 | AE11: =IF(AA11,L11,"") | AF11: =U11 -> 0 | AG11: =AG10+IF(Q11,1,0) -> 0 | AH11: =AG10 -> 0 | AI11: =X11+Y11*(E11-AB11)-Y11*AD11*Inputs!$B$13*(A11-AC11) -> 1000 | AJ11: 0 | AK11: =IF(AND(B11<=U11,NOT(Q11)),B11,U11)*(1-Inputs!$B$12) -> 0
A12: 44796 | B12: 0.83930269 | C12: 0.84436174 | D12: 0.83631403 | E12: 0.83710819 | F12: =IF(ROW()-2>=Inputs!$B$4,AVERAGE(OFFSET(E12,1-Inputs!$B$4,0,Inputs!$B$4,1)),"") | G12: =IF(ROW()-2>=Inputs!$B$5,AVERAGE(OFFSET(E12,1-Inputs!$B$5,0,Inputs!$B$5,1)),"") | H12: =MAX(C12-D12,ABS(C12-E11),ABS(D12-E11)) -> 0.0080477121 | I12: =IF(ROW()-2<14,"",IF(ROW()-2=14,AVERAGE(OFFSET(H12,-13,0,14,1)),(I11*13+H12)/14)) | J12: =IF(AND(ISNUMBER(F12),ISNUMBER(G12),ISNUMBER(F11),ISNUMBER(G11)),AND(F12>G12,F11<=G11),FALSE()) -> FALSE | K12: =IF(AND(ISNUMBER(F12),ISNUMBER(G12),ISNUMBER(F11),ISNUMBER(G11)),AND(F12<G12,F11>=G11),FALSE()) -> FALSE | L12: =IF(ISNUMBER(I12),E12-Inputs!$B$6*I12,"") | M12: =AND(Y11>0,Z11) -> FALSE | N12: =B12*(1-Inputs!$B$12) -> 0.83913483 | O12: =IF(M12,Y11*(N12-AB11)-Inputs!$B$9-Y11*AD11*Inputs!$B$13*(A12-AC11),0) -> 0 | P12: =X11+O12 -> 1000 | Q12: =AND(IF(M12,0,Y11)=0,AA11,IF(ISNUMBER(AE11),B12>AE11,FALSE())) -> FALSE | R12: =B12*(1+Inputs!$B$12) -> 0.83947055 | S12: =IF(Q12,MIN(P12*Inputs!$B$3/(R12-AE11),P12*Inputs!$B$11/R12),0) -> 0 | T12: =IF(Q12,S12,IF(M12,0,Y11)) -> 0 | U12: =IF(Q12,AE11,AF11) -> 0 | V12: =AND(T12>0,D12<=U12) -> FALSE | W12: =IF(V12,T12*(AK12-AB12)-Inputs!$B$9-T12*AD12*Inputs!$B$13*(A12-AC12),0) -> 0 | X12: =P12-IF(Q12,Inputs!$B$9,0)+W12 -> 1000 | Y12: =IF(V12,0,T12) -> 0 | Z12: =AND(Y12>0,K12) -> FALSE | AA12: =AND(Y12=0,J12,ISNUMBER(L12)) -> FALSE | AB12: =IF(Q12,R12,AB11) -> 0 | AC12: =IF(Q12,A12,AC11) -> 0 | AD12: =IF(Q12,B12,AD11) -> 0 | AE12: =IF(AA12,L12,"") | AF12: =U12 -> 0 | AG12: =AG11+IF(Q12,1,0) -> 0 | AH12: =AG11 -> 0 | AI12: =X12+Y12*(E12-AB12)-Y12*AD12*Inputs!$B$13*(A12-AC12) -> 1000 | AJ12: 0 | AK12: =IF(AND(B12<=U12,NOT(Q12)),B12,U12)*(1-Inputs!$B$12) -> 0
A13: 44797 | B13: 0.83710819 | C13: 0.84824459 | D13: 0.83197383 | E13: 0.8439914 | F13: =IF(ROW()-2>=Inputs!$B$4,AVERAGE(OFFSET(E13,1-Inputs!$B$4,0,Inputs!$B$4,1)),"") | G13: =IF(ROW()-2>=Inputs!$B$5,AVERAGE(OFFSET(E13,1-Inputs!$B$5,0,Inputs!$B$5,1)),"") | H13: =MAX(C13-D13,ABS(C13-E12),ABS(D13-E12)) -> 0.016270763 | I13: =IF(ROW()-2<14,"",IF(ROW()-2=14,AVERAGE(OFFSET(H13,-13,0,14,1)),(I12*13+H13)/14)) | J13: =IF(AND(ISNUMBER(F13),ISNUMBER(G13),ISNUMBER(F12),ISNUMBER(G12)),AND(F13>G13,F12<=G12),FALSE()) -> FALSE | K13: =IF(AND(ISNUMBER(F13),ISNUMBER(G13),ISNUMBER(F12),ISNUMBER(G12)),AND(F13<G13,F12>=G12),FALSE()) -> FALSE | L13: =IF(ISNUMBER(I13),E13-Inputs!$B$6*I13,"") | M13: =AND(Y12>0,Z12) -> FALSE | N13: =B13*(1-Inputs!$B$12) -> 0.83694077 | O13: =IF(M13,Y12*(N13-AB12)-Inputs!$B$9-Y12*AD12*Inputs!$B$13*(A13-AC12),0) -> 0 | P13: =X12+O13 -> 1000 | Q13: =AND(IF(M13,0,Y12)=0,AA12,IF(ISNUMBER(AE12),B13>AE12,FALSE())) -> FALSE | R13: =B13*(1+Inputs!$B$12) -> 0.83727561 | S13: =IF(Q13,MIN(P13*Inputs!$B$3/(R13-AE12),P13*Inputs!$B$11/R13),0) -> 0 | T13: =IF(Q13,S13,IF(M13,0,Y12)) -> 0 | U13: =IF(Q13,AE12,AF12) -> 0 | V13: =AND(T13>0,D13<=U13) -> FALSE | W13: =IF(V13,T13*(AK13-AB13)-Inputs!$B$9-T13*AD13*Inputs!$B$13*(A13-AC13),0) -> 0 | X13: =P13-IF(Q13,Inputs!$B$9,0)+W13 -> 1000 | Y13: =IF(V13,0,T13) -> 0 | Z13: =AND(Y13>0,K13) -> FALSE | AA13: =AND(Y13=0,J13,ISNUMBER(L13)) -> FALSE | AB13: =IF(Q13,R13,AB12) -> 0 | AC13: =IF(Q13,A13,AC12) -> 0 | AD13: =IF(Q13,B13,AD12) -> 0 | AE13: =IF(AA13,L13,"") | AF13: =U13 -> 0 | AG13: =AG12+IF(Q13,1,0) -> 0 | AH13: =AG12 -> 0 | AI13: =X13+Y13*(E13-AB13)-Y13*AD13*Inputs!$B$13*(A13-AC13) -> 1000 | AJ13: 0 | AK13: =IF(AND(B13<=U13,NOT(Q13)),B13,U13)*(1-Inputs!$B$12) -> 0
A14: 44798 | B14: 0.8439914 | C14: 0.84797214 | D14: 0.84374077 | E14: 0.84624998 | F14: =IF(ROW()-2>=Inputs!$B$4,AVERAGE(OFFSET(E14,1-Inputs!$B$4,0,Inputs!$B$4,1)),"") | G14: =IF(ROW()-2>=Inputs!$B$5,AVERAGE(OFFSET(E14,1-Inputs!$B$5,0,Inputs!$B$5,1)),"") | H14: =MAX(C14-D14,ABS(C14-E13),ABS(D14-E13)) -> 0.0042313637 | I14: =IF(ROW()-2<14,"",IF(ROW()-2=14,AVERAGE(OFFSET(H14,-13,0,14,1)),(I13*13+H14)/14)) | J14: =IF(AND(ISNUMBER(F14),ISNUMBER(G14),ISNUMBER(F13),ISNUMBER(G13)),AND(F14>G14,F13<=G13),FALSE()) -> FALSE | K14: =IF(AND(ISNUMBER(F14),ISNUMBER(G14),ISNUMBER(F13),ISNUMBER(G13)),AND(F14<G14,F13>=G13),FALSE()) -> FALSE | L14: =IF(ISNUMBER(I14),E14-Inputs!$B$6*I14,"") | M14: =AND(Y13>0,Z13) -> FALSE | N14: =B14*(1-Inputs!$B$12) -> 0.8438226 | O14: =IF(M14,Y13*(N14-AB13)-Inputs!$B$9-Y13*AD13*Inputs!$B$13*(A14-AC13),0) -> 0 | P14: =X13+O14 -> 1000 | Q14: =AND(IF(M14,0,Y13)=0,AA13,IF(ISNUMBER(AE13),B14>AE13,FALSE())) -> FALSE | R14: =B14*(1+Inputs!$B$12) -> 0.8441602 | S14: =IF(Q14,MIN(P14*Inputs!$B$3/(R14-AE13),P14*Inputs!$B$11/R14),0) -> 0 | T14: =IF(Q14,S14,IF(M14,0,Y13)) -> 0 | U14: =IF(Q14,AE13,AF13) -> 0 | V14: =AND(T14>0,D14<=U14) -> FALSE | W14: =IF(V14,T14*(AK14-AB14)-Inputs!$B$9-T14*AD14*Inputs!$B$13*(A14-AC14),0) -> 0 | X14: =P14-IF(Q14,Inputs!$B$9,0)+W14 -> 1000 | Y14: =IF(V14,0,T14) -> 0 | Z14: =AND(Y14>0,K14) -> FALSE | AA14: =AND(Y14=0,J14,ISNUMBER(L14)) -> FALSE | AB14: =IF(Q14,R14,AB13) -> 0 | AC14: =IF(Q14,A14,AC13) -> 0 | AD14: =IF(Q14,B14,AD13) -> 0 | AE14: =IF(AA14,L14,"") | AF14: =U14 -> 0 | AG14: =AG13+IF(Q14,1,0) -> 0 | AH14: =AG13 -> 0 | AI14: =X14+Y14*(E14-AB14)-Y14*AD14*Inputs!$B$13*(A14-AC14) -> 1000 | AJ14: 0 | AK14: =IF(AND(B14<=U14,NOT(Q14)),B14,U14)*(1-Inputs!$B$12) -> 0
A15: 44799 | B15: 0.84624998 | C15: 0.85372987 | D15: 0.84093548 | E15: 0.84779213 | F15: =IF(ROW()-2>=Inputs!$B$4,AVERAGE(OFFSET(E15,1-Inputs!$B$4,0,Inputs!$B$4,1)),"") | G15: =IF(ROW()-2>=Inputs!$B$5,AVERAGE(OFFSET(E15,1-Inputs!$B$5,0,Inputs!$B$5,1)),"") | H15: =MAX(C15-D15,ABS(C15-E14),ABS(D15-E14)) -> 0.012794391 | I15: =IF(ROW()-2<14,"",IF(ROW()-2=14,AVERAGE(OFFSET(H15,-13,0,14,1)),(I14*13+H15)/14)) | J15: =IF(AND(ISNUMBER(F15),ISNUMBER(G15),ISNUMBER(F14),ISNUMBER(G14)),AND(F15>G15,F14<=G14),FALSE()) -> FALSE | K15: =IF(AND(ISNUMBER(F15),ISNUMBER(G15),ISNUMBER(F14),ISNUMBER(G14)),AND(F15<G15,F14>=G14),FALSE()) -> FALSE | L15: =IF(ISNUMBER(I15),E15-Inputs!$B$6*I15,"") | M15: =AND(Y14>0,Z14) -> FALSE | N15: =B15*(1-Inputs!$B$12) -> 0.84608073 | O15: =IF(M15,Y14*(N15-AB14)-Inputs!$B$9-Y14*AD14*Inputs!$B$13*(A15-AC14),0) -> 0 | P15: =X14+O15 -> 1000 | Q15: =AND(IF(M15,0,Y14)=0,AA14,IF(ISNUMBER(AE14),B15>AE14,FALSE())) -> FALSE | R15: =B15*(1+Inputs!$B$12) -> 0.84641923 | S15: =IF(Q15,MIN(P15*Inputs!$B$3/(R15-AE14),P15*Inputs!$B$11/R15),0) -> 0 | T15: =IF(Q15,S15,IF(M15,0,Y14)) -> 0 | U15: =IF(Q15,AE14,AF14) -> 0 | V15: =AND(T15>0,D15<=U15) -> FALSE | W15: =IF(V15,T15*(AK15-AB15)-Inputs!$B$9-T15*AD15*Inputs!$B$13*(A15-AC15),0) -> 0 | X15: =P15-IF(Q15,Inputs!$B$9,0)+W15 -> 1000 | Y15: =IF(V15,0,T15) -> 0 | Z15: =AND(Y15>0,K15) -> FALSE | AA15: =AND(Y15=0,J15,ISNUMBER(L15)) -> FALSE | AB15: =IF(Q15,R15,AB14) -> 0 | AC15: =IF(Q15,A15,AC14) -> 0 | AD15: =IF(Q15,B15,AD14) -> 0 | AE15: =IF(AA15,L15,"") | AF15: =U15 -> 0 | AG15: =AG14+IF(Q15,1,0) -> 0 | AH15: =AG14 -> 0 | AI15: =X15+Y15*(E15-AB15)-Y15*AD15*Inputs!$B$13*(A15-AC15) -> 1000 | AJ15: 0 | AK15: =IF(AND(B15<=U15,NOT(Q15)),B15,U15)*(1-Inputs!$B$12) -> 0
... A1501: 46285 | B1501: 0.79524076 | C1501: 0.79791563 | D1501: 0.79048315 | E1501: 0.79053229 | F1501: =IF(ROW()-2>=Inputs!$B$4,AVERAGE(OFFSET(E1501,1-Inputs!$B$4,0,Inputs!$B$4,1)),"") -> 0.81710508 | G1501: =IF(ROW()-2>=Inputs!$B$5,AVERAGE(OFFSET(E1501,1-Inputs!$B$5,0,Inputs!$B$5,1)),"") -> 0.82388876 | H1501: =MAX(C1501-D1501,ABS(C1501-E1500),ABS(D1501-E1500)) -> 0.0074324759 | I1501: =IF(ROW()-2<14,"",IF(ROW()-2=14,AVERAGE(OFFSET(H1501,-13,0,14,1)),(I1500*13+H1501)/14)) -> 0.0084609091 | J1501: =IF(AND(ISNUMBER(F1501),ISNUMBER(G1501),ISNUMBER(F1500),ISNUMBER(G1500)),AND(F1501>G1501,F1500<=G1500),FALSE()) -> FALSE | K1501: =IF(AND(ISNUMBER(F1501),ISNUMBER(G1501),ISNUMBER(F1500),ISNUMBER(G1500)),AND(F1501<G1501,F1500>=G1500),FALSE()) -> FALSE | L1501: =IF(ISNUMBER(I1501),E1501-Inputs!$B$6*I1501,"") -> 0.77361047 | M1501: =AND(Y1500>0,Z1500) -> FALSE | N1501: =B1501*(1-Inputs!$B$12) -> 0.79508171 | O1501: =IF(M1501,Y1500*(N1501-AB1500)-Inputs!$B$9-Y1500*AD1500*Inputs!$B$13*(A1501-AC1500),0) -> 0 | P1501: =X1500+O1501 -> 892.96682 | Q1501: =AND(IF(M1501,0,Y1500)=0,AA1500,IF(ISNUMBER(AE1500),B1501>AE1500,FALSE())) -> FALSE | R1501: =B1501*(1+Inputs!$B$12) -> 0.7953998 | S1501: =IF(Q1501,MIN(P1501*Inputs!$B$3/(R1501-AE1500),P1501*Inputs!$B$11/R1501),0) -> 0 | T1501: =IF(Q1501,S1501,IF(M1501,0,Y1500)) -> 0 | U1501: =IF(Q1501,AE1500,AF1500) -> 0.84743438 | V1501: =AND(T1501>0,D1501<=U1501) -> FALSE | W1501: =IF(V1501,T1501*(AK1501-AB1501)-Inputs!$B$9-T1501*AD1501*Inputs!$B$13*(A1501-AC1501),0) -> 0 | X1501: =P1501-IF(Q1501,Inputs!$B$9,0)+W1501 -> 892.96682 | Y1501: =IF(V1501,0,T1501) -> 0 | Z1501: =AND(Y1501>0,K1501) -> FALSE | AA1501: =AND(Y1501=0,J1501,ISNUMBER(L1501)) -> FALSE | AB1501: =IF(Q1501,R1501,AB1500) -> 0.86624978 | AC1501: =IF(Q1501,A1501,AC1500) -> 46233 | AD1501: =IF(Q1501,B1501,AD1500) -> 0.86607657 | AE1501: =IF(AA1501,L1501,"") | AF1501: =U1501 -> 0.84743438 | AG1501: =AG1500+IF(Q1501,1,0) -> 17 | AH1501: =AG1500 -> 17 | AI1501: =X1501+Y1501*(E1501-AB1501)-Y1501*AD1501*Inputs!$B$13*(A1501-AC1501) -> 892.96682 | AJ1501: 0 | AK1501: =IF(AND(B1501<=U1501,NOT(Q1501)),B1501,U1501)*(1-Inputs!$B$12) -> 0.79508171
A1502: 46286 | B1502: 0.79053229 | C1502: 0.79247208 | D1502: 0.78608731 | E1502: 0.78650529 | F1502: =IF(ROW()-2>=Inputs!$B$4,AVERAGE(OFFSET(E1502,1-Inputs!$B$4,0,Inputs!$B$4,1)),"") -> 0.81512195 | G1502: =IF(ROW()-2>=Inputs!$B$5,AVERAGE(OFFSET(E1502,1-Inputs!$B$5,0,Inputs!$B$5,1)),"") -> 0.82246357 | H1502: =MAX(C1502-D1502,ABS(C1502-E1501),ABS(D1502-E1501)) -> 0.0063847733 | I1502: =IF(ROW()-2<14,"",IF(ROW()-2=14,AVERAGE(OFFSET(H1502,-13,0,14,1)),(I1501*13+H1502)/14)) -> 0.0083126137 | J1502: =IF(AND(ISNUMBER(F1502),ISNUMBER(G1502),ISNUMBER(F1501),ISNUMBER(G1501)),AND(F1502>G1502,F1501<=G1501),FALSE()) -> FALSE | K1502: =IF(AND(ISNUMBER(F1502),ISNUMBER(G1502),ISNUMBER(F1501),ISNUMBER(G1501)),AND(F1502<G1502,F1501>=G1501),FALSE()) -> FALSE | L1502: =IF(ISNUMBER(I1502),E1502-Inputs!$B$6*I1502,"") -> 0.76988006 | M1502: =AND(Y1501>0,Z1501) -> FALSE | N1502: =B1502*(1-Inputs!$B$12) -> 0.79037418 | O1502: =IF(M1502,Y1501*(N1502-AB1501)-Inputs!$B$9-Y1501*AD1501*Inputs!$B$13*(A1502-AC1501),0) -> 0 | P1502: =X1501+O1502 -> 892.96682 | Q1502: =AND(IF(M1502,0,Y1501)=0,AA1501,IF(ISNUMBER(AE1501),B1502>AE1501,FALSE())) -> FALSE | R1502: =B1502*(1+Inputs!$B$12) -> 0.79069039 | S1502: =IF(Q1502,MIN(P1502*Inputs!$B$3/(R1502-AE1501),P1502*Inputs!$B$11/R1502),0) -> 0 | T1502: =IF(Q1502,S1502,IF(M1502,0,Y1501)) -> 0 | U1502: =IF(Q1502,AE1501,AF1501) -> 0.84743438 | V1502: =AND(T1502>0,D1502<=U1502) -> FALSE | W1502: =IF(V1502,T1502*(AK1502-AB1502)-Inputs!$B$9-T1502*AD1502*Inputs!$B$13*(A1502-AC1502),0) -> 0 | X1502: =P1502-IF(Q1502,Inputs!$B$9,0)+W1502 -> 892.96682 | Y1502: =IF(V1502,0,T1502) -> 0 | Z1502: =AND(Y1502>0,K1502) -> FALSE | AA1502: =AND(Y1502=0,J1502,ISNUMBER(L1502)) -> FALSE | AB1502: =IF(Q1502,R1502,AB1501) -> 0.86624978 | AC1502: =IF(Q1502,A1502,AC1501) -> 46233 | AD1502: =IF(Q1502,B1502,AD1501) -> 0.86607657 | AE1502: =IF(AA1502,L1502,"") | AF1502: =U1502 -> 0.84743438 | AG1502: =AG1501+IF(Q1502,1,0) -> 17 | AH1502: =AG1501 -> 17 | AI1502: =X1502+Y1502*(E1502-AB1502)-Y1502*AD1502*Inputs!$B$13*(A1502-AC1502) -> 892.96682 | AJ1502: =IF(Y1502>0,Y1502*(E1502*(1-Inputs!$B$12)-AB1502)-Inputs!$B$9-Y1502*AD1502*Inputs!$B$13*(A1502-AC1502),0) -> 0 | AK1502: =IF(AND(B1502<=U1502,NOT(Q1502)),B1502,U1502)*(1-Inputs!$B$12) -> 0.79037418

Sheet Trades
A1: Trade | B1: Entry date (app) | C1: Entry date (sheet) | D1: Buy fill (app) | E1: Buy fill (sheet) | F1: Units (app) | G1: Units (sheet) | H1: Exit (app) | I1: Profit £ (app) | J1: Profit £ (sheet) | K1: Difference £ | L1: Match?
A2: 1 | B2: 44890 | C2: =INDEX(Calc!$A$3:$A$1502,MATCH(1,Calc!$AG$3:$AG$1502,0)) -> 44890 | D2: 0.86197666 | E2: =INDEX(Calc!$R$3:$R$1502,MATCH(1,Calc!$AG$3:$AG$1502,0)) -> 0.86197666 | F2: 515.9512 | G2: =INDEX(Calc!$S$3:$S$1502,MATCH(1,Calc!$AG$3:$AG$1502,0)) -> 515.9512 | H2: Fast average crosses back below the slow average | I2: 29.927372 | J2: =SUMIF(Calc!$AH$3:$AH$1502,1,Calc!$O$3:$O$1502)+SUMIF(Calc!$AG$3:$AG$1502,1,Calc!$W$3:$W$1502)+SUMIF(Calc!$AG$3:$AG$1502,1,Calc!$AJ$3:$AJ$1502)-Inputs!$B$9 -> 29.927372 | K2: =J2-I2 -> -4.0239519e-07 | L2: =AND(ABS(K2)<0.005,C2=B2,ABS(E2-D2)<0.0000001,ABS(G2-F2)<0.0001) -> TRUE
A3: 2 | B3: 45034 | C3: =INDEX(Calc!$A$3:$A$1502,MATCH(2,Calc!$AG$3:$AG$1502,0)) -> 45034 | D3: 0.95824965 | E3: =INDEX(Calc!$R$3:$R$1502,MATCH(2,Calc!$AG$3:$AG$1502,0)) -> 0.95824965 | F3: 516.99069 | G3: =INDEX(Calc!$S$3:$S$1502,MATCH(2,Calc!$AG$3:$AG$1502,0)) -> 516.99069 | H3: Stop-loss | I3: -13.542965 | J3: =SUMIF(Calc!$AH$3:$AH$1502,2,Calc!$O$3:$O$1502)+SUMIF(Calc!$AG$3:$AG$1502,2,Calc!$W$3:$W$1502)+SUMIF(Calc!$AG$3:$AG$1502,2,Calc!$AJ$3:$AJ$1502)-Inputs!$B$9 -> -13.542965 | K3: =J3-I3 -> 8.2491367e-08 | L3: =AND(ABS(K3)<0.005,C3=B3,ABS(E3-D3)<0.0000001,ABS(G3-F3)<0.0001) -> TRUE
A4: 3 | B4: 45226 | C4: =INDEX(Calc!$A$3:$A$1502,MATCH(3,Calc!$AG$3:$AG$1502,0)) -> 45226 | D4: 0.78728648 | E4: =INDEX(Calc!$R$3:$R$1502,MATCH(3,Calc!$AG$3:$AG$1502,0)) -> 0.78728648 | F4: 664.11897 | G4: =INDEX(Calc!$S$3:$S$1502,MATCH(3,Calc!$AG$3:$AG$1502,0)) -> 664.11897 | H4: Fast average crosses back below the slow average | I4: 33.971256 | J4: =SUMIF(Calc!$AH$3:$AH$1502,3,Calc!$O$3:$O$1502)+SUMIF(Calc!$AG$3:$AG$1502,3,Calc!$W$3:$W$1502)+SUMIF(Calc!$AG$3:$AG$1502,3,Calc!$AJ$3:$AJ$1502)-Inputs!$B$9 -> 33.971256 | K4: =J4-I4 -> -2.8482206e-07 | L4: =AND(ABS(K4)<0.005,C4=B4,ABS(E4-D4)<0.0000001,ABS(G4-F4)<0.0001) -> TRUE
A5: 4 | B5: 45375 | C5: =INDEX(Calc!$A$3:$A$1502,MATCH(4,Calc!$AG$3:$AG$1502,0)) -> 45375 | D5: 0.86806597 | E5: =INDEX(Calc!$R$3:$R$1502,MATCH(4,Calc!$AG$3:$AG$1502,0)) -> 0.86806597 | F5: 598.20101 | G5: =INDEX(Calc!$S$3:$S$1502,MATCH(4,Calc!$AG$3:$AG$1502,0)) -> 598.20101 | H5: Stop-loss | I5: -13.252501 | J5: =SUMIF(Calc!$AH$3:$AH$1502,4,Calc!$O$3:$O$1502)+SUMIF(Calc!$AG$3:$AG$1502,4,Calc!$W$3:$W$1502)+SUMIF(Calc!$AG$3:$AG$1502,4,Calc!$AJ$3:$AJ$1502)-Inputs!$B$9 -> -13.252501 | K5: =J5-I5 -> -1.3079516e-07 | L5: =AND(ABS(K5)<0.005,C5=B5,ABS(E5-D5)<0.0000001,ABS(G5-F5)<0.0001) -> TRUE
A6: 5 | B6: 45463 | C6: =INDEX(Calc!$A$3:$A$1502,MATCH(5,Calc!$AG$3:$AG$1502,0)) -> 45463 | D6: 0.92419462 | E6: =INDEX(Calc!$R$3:$R$1502,MATCH(5,Calc!$AG$3:$AG$1502,0)) -> 0.92419462 | F6: 559.75478 | G6: =INDEX(Calc!$S$3:$S$1502,MATCH(5,Calc!$AG$3:$AG$1502,0)) -> 559.75478 | H6: Stop-loss | I6: -15.511969 | J6: =SUMIF(Calc!$AH$3:$AH$1502,5,Calc!$O$3:$O$1502)+SUMIF(Calc!$AG$3:$AG$1502,5,Calc!$W$3:$W$1502)+SUMIF(Calc!$AG$3:$AG$1502,5,Calc!$AJ$3:$AJ$1502)-Inputs!$B$9 -> -15.511969 | K6: =J6-I6 -> 3.5297239e-07 | L6: =AND(ABS(K6)<0.005,C6=B6,ABS(E6-D6)<0.0000001,ABS(G6-F6)<0.0001) -> TRUE
A7: 6 | B7: 45543 | C7: =INDEX(Calc!$A$3:$A$1502,MATCH(6,Calc!$AG$3:$AG$1502,0)) -> 45543 | D7: 0.90109882 | E7: =INDEX(Calc!$R$3:$R$1502,MATCH(6,Calc!$AG$3:$AG$1502,0)) -> 0.90109882 | F7: 520.76641 | G7: =INDEX(Calc!$S$3:$S$1502,MATCH(6,Calc!$AG$3:$AG$1502,0)) -> 520.76641 | H7: Stop-loss | I7: -12.725474 | J7: =SUMIF(Calc!$AH$3:$AH$1502,6,Calc!$O$3:$O$1502)+SUMIF(Calc!$AG$3:$AG$1502,6,Calc!$W$3:$W$1502)+SUMIF(Calc!$AG$3:$AG$1502,6,Calc!$AJ$3:$AJ$1502)-Inputs!$B$9 -> -12.725474 | K7: =J7-I7 -> 3.8571845e-07 | L7: =AND(ABS(K7)<0.005,C7=B7,ABS(E7-D7)<0.0000001,ABS(G7-F7)<0.0001) -> TRUE
A8: 7 | B8: 45562 | C8: =INDEX(Calc!$A$3:$A$1502,MATCH(7,Calc!$AG$3:$AG$1502,0)) -> 45562 | D8: 0.90879464 | E8: =INDEX(Calc!$R$3:$R$1502,MATCH(7,Calc!$AG$3:$AG$1502,0)) -> 0.90879464 | F8: 516.15596 | G8: =INDEX(Calc!$S$3:$S$1502,MATCH(7,Calc!$AG$3:$AG$1502,0)) -> 516.15596 | H8: Stop-loss | I8: -12.681564 | J8: =SUMIF(Calc!$AH$3:$AH$1502,7,Calc!$O$3:$O$1502)+SUMIF(Calc!$AG$3:$AG$1502,7,Calc!$W$3:$W$1502)+SUMIF(Calc!$AG$3:$AG$1502,7,Calc!$AJ$3:$AJ$1502)-Inputs!$B$9 -> -12.681564 | K8: =J8-I8 -> 2.8760247e-07 | L8: =AND(ABS(K8)<0.005,C8=B8,ABS(E8-D8)<0.0000001,ABS(G8-F8)<0.0001) -> TRUE
A9: 8 | B9: 45628 | C9: =INDEX(Calc!$A$3:$A$1502,MATCH(8,Calc!$AG$3:$AG$1502,0)) -> 45628 | D9: 0.8633397 | E9: =INDEX(Calc!$R$3:$R$1502,MATCH(8,Calc!$AG$3:$AG$1502,0)) -> 0.8633397 | F9: 570.09791 | G9: =INDEX(Calc!$S$3:$S$1502,MATCH(8,Calc!$AG$3:$AG$1502,0)) -> 570.09791 | H9: Stop-loss | I9: -12.321184 | J9: =SUMIF(Calc!$AH$3:$AH$1502,8,Calc!$O$3:$O$1502)+SUMIF(Calc!$AG$3:$AG$1502,8,Calc!$W$3:$W$1502)+SUMIF(Calc!$AG$3:$AG$1502,8,Calc!$AJ$3:$AJ$1502)-Inputs!$B$9 -> -12.321184 | K9: =J9-I9 -> -7.4053577e-08 | L9: =AND(ABS(K9)<0.005,C9=B9,ABS(E9-D9)<0.0000001,ABS(G9-F9)<0.0001) -> TRUE
A10: 9 | B10: 45706 | C10: =INDEX(Calc!$A$3:$A$1502,MATCH(9,Calc!$AG$3:$AG$1502,0)) -> 45706 | D10: 0.86350344 | E10: =INDEX(Calc!$R$3:$R$1502,MATCH(9,Calc!$AG$3:$AG$1502,0)) -> 0.86350344 | F10: 500.05621 | G10: =INDEX(Calc!$S$3:$S$1502,MATCH(9,Calc!$AG$3:$AG$1502,0)) -> 500.05621 | H10: Stop-loss | I10: -13.460633 | J10: =SUMIF(Calc!$AH$3:$AH$1502,9,Calc!$O$3:$O$1502)+SUMIF(Calc!$AG$3:$AG$1502,9,Calc!$W$3:$W$1502)+SUMIF(Calc!$AG$3:$AG$1502,9,Calc!$AJ$3:$AJ$1502)-Inputs!$B$9 -> -13.460633 | K10: =J10-I10 -> -2.4963882e-07 | L10: =AND(ABS(K10)<0.005,C10=B10,ABS(E10-D10)<0.0000001,ABS(G10-F10)<0.0001) -> TRUE
A11: 10 | B11: 45816 | C11: =INDEX(Calc!$A$3:$A$1502,MATCH(10,Calc!$AG$3:$AG$1502,0)) -> 45816 | D11: 0.84680616 | E11: =INDEX(Calc!$R$3:$R$1502,MATCH(10,Calc!$AG$3:$AG$1502,0)) -> 0.84680616 | F11: 533.56179 | G11: =INDEX(Calc!$S$3:$S$1502,MATCH(10,Calc!$AG$3:$AG$1502,0)) -> 533.56179 | H11: Stop-loss | I11: -12.516458 | J11: =SUMIF(Calc!$AH$3:$AH$1502,10,Calc!$O$3:$O$1502)+SUMIF(Calc!$AG$3:$AG$1502,10,Calc!$W$3:$W$1502)+SUMIF(Calc!$AG$3:$AG$1502,10,Calc!$AJ$3:$AJ$1502)-Inputs!$B$9 -> -12.516458 | K11: =J11-I11 -> 2.2547522e-07 | L11: =AND(ABS(K11)<0.005,C11=B11,ABS(E11-D11)<0.0000001,ABS(G11-F11)<0.0001) -> TRUE
A12: 11 | B12: 45834 | C12: =INDEX(Calc!$A$3:$A$1502,MATCH(11,Calc!$AG$3:$AG$1502,0)) -> 45834 | D12: 0.8571842 | E12: =INDEX(Calc!$R$3:$R$1502,MATCH(11,Calc!$AG$3:$AG$1502,0)) -> 0.8571842 | F12: 556.77277 | G12: =INDEX(Calc!$S$3:$S$1502,MATCH(11,Calc!$AG$3:$AG$1502,0)) -> 556.77277 | H12: Stop-loss | I12: -12.267212 | J12: =SUMIF(Calc!$AH$3:$AH$1502,11,Calc!$O$3:$O$1502)+SUMIF(Calc!$AG$3:$AG$1502,11,Calc!$W$3:$W$1502)+SUMIF(Calc!$AG$3:$AG$1502,11,Calc!$AJ$3:$AJ$1502)-Inputs!$B$9 -> -12.267212 | K12: =J12-I12 -> -1.3273391e-08 | L12: =AND(ABS(K12)<0.005,C12=B12,ABS(E12-D12)<0.0000001,ABS(G12-F12)<0.0001) -> TRUE
A13: 12 | B13: 45888 | C13: =INDEX(Calc!$A$3:$A$1502,MATCH(12,Calc!$AG$3:$AG$1502,0)) -> 45888 | D13: 0.85213956 | E13: =INDEX(Calc!$R$3:$R$1502,MATCH(12,Calc!$AG$3:$AG$1502,0)) -> 0.85213956 | F13: 572.57507 | G13: =INDEX(Calc!$S$3:$S$1502,MATCH(12,Calc!$AG$3:$AG$1502,0)) -> 572.57507 | H13: Fast average crosses back below the slow average | I13: 4.111547 | J13: =SUMIF(Calc!$AH$3:$AH$1502,12,Calc!$O$3:$O$1502)+SUMIF(Calc!$AG$3:$AG$1502,12,Calc!$W$3:$W$1502)+SUMIF(Calc!$AG$3:$AG$1502,12,Calc!$AJ$3:$AJ$1502)-Inputs!$B$9 -> 4.1115474 | K13: =J13-I13 -> 4.0427748e-07 | L13: =AND(ABS(K13)<0.005,C13=B13,ABS(E13-D13)<0.0000001,ABS(G13-F13)<0.0001) -> TRUE
A14: 13 | B14: 46007 | C14: =INDEX(Calc!$A$3:$A$1502,MATCH(13,Calc!$AG$3:$AG$1502,0)) -> 46007 | D14: 0.91052954 | E14: =INDEX(Calc!$R$3:$R$1502,MATCH(13,Calc!$AG$3:$AG$1502,0)) -> 0.91052954 | F14: 506.82242 | G14: =INDEX(Calc!$S$3:$S$1502,MATCH(13,Calc!$AG$3:$AG$1502,0)) -> 506.82242 | H14: Stop-loss | I14: -12.409342 | J14: =SUMIF(Calc!$AH$3:$AH$1502,13,Calc!$O$3:$O$1502)+SUMIF(Calc!$AG$3:$AG$1502,13,Calc!$W$3:$W$1502)+SUMIF(Calc!$AG$3:$AG$1502,13,Calc!$AJ$3:$AJ$1502)-Inputs!$B$9 -> -12.409342 | K14: =J14-I14 -> 2.9978374e-07 | L14: =AND(ABS(K14)<0.005,C14=B14,ABS(E14-D14)<0.0000001,ABS(G14-F14)<0.0001) -> TRUE
A15: 14 | B15: 46049 | C15: =INDEX(Calc!$A$3:$A$1502,MATCH(14,Calc!$AG$3:$AG$1502,0)) -> 46049 | D15: 0.90291705 | E15: =INDEX(Calc!$R$3:$R$1502,MATCH(14,Calc!$AG$3:$AG$1502,0)) -> 0.90291705 | F15: 527.19381 | G15: =INDEX(Calc!$S$3:$S$1502,MATCH(14,Calc!$AG$3:$AG$1502,0)) -> 527.19381 | H15: Stop-loss | I15: -11.975051 | J15: =SUMIF(Calc!$AH$3:$AH$1502,14,Calc!$O$3:$O$1502)+SUMIF(Calc!$AG$3:$AG$1502,14,Calc!$W$3:$W$1502)+SUMIF(Calc!$AG$3:$AG$1502,14,Calc!$AJ$3:$AJ$1502)-Inputs!$B$9 -> -11.975051 | K15: =J15-I15 -> 2.8904604e-07 | L15: =AND(ABS(K15)<0.005,C15=B15,ABS(E15-D15)<0.0000001,ABS(G15-F15)<0.0001) -> TRUE
A16: 15 | B16: 46112 | C16: =INDEX(Calc!$A$3:$A$1502,MATCH(15,Calc!$AG$3:$AG$1502,0)) -> 46112 | D16: 0.87407732 | E16: =INDEX(Calc!$R$3:$R$1502,MATCH(15,Calc!$AG$3:$AG$1502,0)) -> 0.87407732 | F16: 474.91078 | G16: =INDEX(Calc!$S$3:$S$1502,MATCH(15,Calc!$AG$3:$AG$1502,0)) -> 474.91078 | H16: Stop-loss | I16: -13.034529 | J16: =SUMIF(Calc!$AH$3:$AH$1502,15,Calc!$O$3:$O$1502)+SUMIF(Calc!$AG$3:$AG$1502,15,Calc!$W$3:$W$1502)+SUMIF(Calc!$AG$3:$AG$1502,15,Calc!$AJ$3:$AJ$1502)-Inputs!$B$9 -> -13.034529 | K16: =J16-I16 -> -2.1995293e-07 | L16: =AND(ABS(K16)<0.005,C16=B16,ABS(E16-D16)<0.0000001,ABS(G16-F16)<0.0001) -> TRUE
A17: 16 | B17: 46192 | C17: =INDEX(Calc!$A$3:$A$1502,MATCH(16,Calc!$AG$3:$AG$1502,0)) -> 46192 | D17: 0.83051321 | E17: =INDEX(Calc!$R$3:$R$1502,MATCH(16,Calc!$AG$3:$AG$1502,0)) -> 0.83051321 | F17: 524.31495 | G17: =INDEX(Calc!$S$3:$S$1502,MATCH(16,Calc!$AG$3:$AG$1502,0)) -> 524.31495 | H17: Fast average crosses back below the slow average | I17: -7.847661 | J17: =SUMIF(Calc!$AH$3:$AH$1502,16,Calc!$O$3:$O$1502)+SUMIF(Calc!$AG$3:$AG$1502,16,Calc!$W$3:$W$1502)+SUMIF(Calc!$AG$3:$AG$1502,16,Calc!$AJ$3:$AJ$1502)-Inputs!$B$9 -> -7.8476609 | K17: =J17-I17 -> 9.9496442e-08 | L17: =AND(ABS(K17)<0.005,C17=B17,ABS(E17-D17)<0.0000001,ABS(G17-F17)<0.0001) -> TRUE
A18: 17 | B18: 46233 | C18: =INDEX(Calc!$A$3:$A$1502,MATCH(17,Calc!$AG$3:$AG$1502,0)) -> 46233 | D18: 0.86624978 | E18: =INDEX(Calc!$R$3:$R$1502,MATCH(17,Calc!$AG$3:$AG$1502,0)) -> 0.86624978 | F18: 480.70391 | G18: =INDEX(Calc!$S$3:$S$1502,MATCH(17,Calc!$AG$3:$AG$1502,0)) -> 480.70391 | H18: Stop-loss | I18: -11.496811 | J18: =SUMIF(Calc!$AH$3:$AH$1502,17,Calc!$O$3:$O$1502)+SUMIF(Calc!$AG$3:$AG$1502,17,Calc!$W$3:$W$1502)+SUMIF(Calc!$AG$3:$AG$1502,17,Calc!$AJ$3:$AJ$1502)-Inputs!$B$9 -> -11.496811 | K18: =J18-I18 -> 8.2354235e-08 | L18: =AND(ABS(K18)<0.005,C18=B18,ABS(E18-D18)<0.0000001,ABS(G18-F18)<0.0001) -> TRUE

Sheet Summary
B1: App | C1: Spreadsheet | D1: Match?
A2: Number of trades | B2: 17 | C2: =MAX(Calc!$AG$3:$AG$1502) -> 17 | D2: =B2=C2 -> TRUE
A3: Final balance (£) | B3: 892.96682 | C3: =Calc!X1502+Calc!AJ1502 -> 892.96682 | D3: =ABS(B3-C3)<0.01 -> TRUE
A4: Trades matching | B4: 17 | C4: =COUNTIF(Trades!L2:L18,TRUE()) -> 17 | D4: =B4=C4 -> TRUE
A5: GATE | D5: =AND(D2,D3,D4) -> TRUE
